[{"run_id": 7996775160, "name": "\u508d\u665a\u8dd1\u6b65", "distance": 6151.6, "moving_time": "0:43:32", "type": "Run", "start_date": "2022-10-21 12:02:47+00:00", "start_date_local": "2022-10-21 20:02:47", "location_country": "\u5929\u9e45\u6e56, \u7941\u95e8\u8def, \u8377\u53f6\u5730\u8857\u9053, \u5408\u80a5\u653f\u52a1\u6587\u5316\u65b0\u533a, \u8700\u5c71\u533a, \u5408\u80a5\u5e02, \u5b89\u5fbd\u7701, 230031, \u4e2d\u56fd", "summary_polyline": "a`daEqnnjU?]EEC[IYE?ENKHI@QKIKEMOSUK[WGQGCKKMAGMUSQUWSQW?WG@CDa@ASJ_@AYBWFKLCRILe@PU?WKOUYGQAa@H]PEFg@NW@_@M_@EuAd@OBULa@CUESBMJOZAXBJMv@?VOZQPEn@c@h@ELOVGR@f@IZe@TG@SLILU~@INCBM\\A\\Mv@@TGP@JJFGp@ITDXAJDRRv@Fd@HV\\r@@HNXPTJHJ@RPd@JL@TJH?JDDDFNDPCFDb@P`@NFFAp@JZRT^?JDHCJQRQXK^GDU\\e@l@ENCf@FFl@@RCER]h@Cj@@RLRZTF`@HRFD\\PZ@FDTBb@@VJHHNV@NC\\BLV|@NTDb@R\\ZZN`@D`@Cf@GNMNKTOh@WZOd@Ch@F|@Ld@b@pADT@ZGn@Bf@GPUPGNa@`@u@ZQLUj@AJCFAl@CXJvAJP@RAJFd@ABOHK`@KJGPOBGJMFa@ZSV[JCFMDGFK@MHUDKFWDOD{@FQDMAEEc@F[KEBKCK@]TADURG@MLKDORs@b@UHMJO@QHa@HIEi@EMIWG_@A]H]^Qd@EV@\\H\\@ZAFWZ@HQ^VHLN`@T`@Nf@FBEGQD[CMFMDEHMP@DCDUG]DIl@i@x@EFCN?n@Qt@o@`A}Aj@U~@Mx@E`AAXFVGXCPKBIZ[FALKNBRWNC~@m@f@g@NgACa@B}@EEl@cAJIHCLITEd@B`@HRETM\\q@D[?W[m@EUIMCeAL]DYJQDOFETe@PMT[NGZ]XQHDDFDB?FFDTFXAJC^Yh@MZ@JKFM?SJc@AQEYWs@GYGQ@[CUAq@Jc@l@y@HU@]C{A@QEo@Uc@SOk@s@SKEOGEEK[IMGUCOBECQCOKKCSWMi@Je@`@OH?BCRC\\IPSVSRUNMTYRQ^g@DCPYLIJCHMVMFQRQFg@Ek@Jm@Ra@C[JQDO?QEMFG@GSg@", "average_heartrate": null, "average_speed": 2.355, "streak": 1}, {"run_id": 8061767531, "name": "\u508d\u665a\u8dd1\u6b65", "distance": 4648.9, "moving_time": "0:30:31", "type": "Run", "start_date": "2022-11-03 10:13:59+00:00", "start_date_local": "2022-11-03 18:13:59", "location_country": "\u671b\u6c5f\u897f\u8def, \u957f\u5b81\u793e\u533a\u670d\u52a1\u4e2d\u5fc3, \u5408\u80a5\u56fd\u5bb6\u9ad8\u65b0\u6280\u672f\u4ea7\u4e1a\u5f00\u53d1\u533a, \u8700\u5c71\u533a, \u5408\u80a5\u5e02, \u5b89\u5fbd\u7701, \u4e2d\u56fd", "summary_polyline": "_lhaEyzxiU@bAC`A@p@Cb@@rAK|@@PCf@?x@CV@\\CzAI`@KVSLG?eARaB^IDs@Jk@Ni@Ba@?iAOc@Oa@U][{AgBMUEUCWCI?cAGi@K]M[SQ[SQEOIOKY_@a@cAKi@CgAQq@IOGUU[g@e@]KQC[C[?q@HWJsARs@AOEUBQCw@AOCW?k@Di@PKHk@Rk@^_@l@OZKNOJ[Ni@Ni@Ae@Mg@]USS_@M]I_@EISaAg@}@a@e@_Ay@o@[k@IOGOOOa@Qu@Ea@?a@CSAy@ImA?i@F]BE^UzBaAr@i@`@cAFk@DeBVgBXaA@KEM]O}@Mk@CGC[CUG@W`@}@BIR_@NOHOTSZe@~@eATMX_@n@e@Zk@LKzAu@^IVOx@ONKbCs@L?t@KlAIn@@XCr@DLAl@B^HdAHXHr@NpA^z@^H@\\RXJ?DG?ODWAOD[V@H|@f@NNhAj@t@h@tAp@^h@JTJ|@D`BALHhAA^JdAHPLP^N\\Bz@BPB|CfCLP", "average_heartrate": null, "average_speed": 2.539, "streak": 1}, {"run_id": 8070470139, "name": "\u5348\u540e\u8dd1\u6b65", "distance": 5200.3, "moving_time": "0:34:58", "type": "Run", "start_date": "2022-11-05 08:53:20+00:00", "start_date_local": "2022-11-05 16:53:20", "location_country": "\u96c6\u8d24\u8def, \u5174\u56ed\u7b2c\u4e8c, \u5174\u56ed\u793e\u533a\u670d\u52a1\u4e2d\u5fc3, \u5408\u80a5\u56fd\u5bb6\u9ad8\u65b0\u6280\u672f\u4ea7\u4e1a\u5f00\u53d1\u533a, \u8700\u5c71\u533a, \u5408\u80a5\u5e02, \u5b89\u5fbd\u7701, 231200, \u4e2d\u56fd", "summary_polyline": "mseaEihjjU?AKCo@s@QG][o@UGAUOSEsAy@SEQKWIMASIK?[KQKYIa@Ie@Ys@UGGOCCBYAQ@IEOAECUGe@u@Oe@KQMc@@e@F[FWPO\\c@XYp@sALIFKNg@FCTa@@AHPVPJLjAv@~@t@n@`@\\Zp@`@FHXRl@V`@ZNNx@l@~@|@VNVRNBRPNHLJNFtAz@^^b@h@`@\\D?v@`@jAnAd@Tn@f@b@PXTJBHFZf@LDPTd@Z^NLTLJx@l@TT@?^Xr@b@HLXPBA\\^j@b@DJPTLHF?DB@FJDIMC??BE?Y_@EMMEMQi@g@g@[OQQKEAMIISUSSOC?c@UKMGEAIq@a@{@s@QI]a@e@YQQQEYOgAkAsA{@MCWKe@[eAiAa@WCIIKQEIIQG[Wa@KOMSKOQSKIMEAIKQMGOKCAIMKSWWMEIg@O_@WKCIKK?[_@e@]k@_@UKSSq@[_A{@I?a@YSYSOF_@LW@UVkAZKB@BRHL?FFHANW@KFICGO@WFQEs@BFaAIMBKHG?AHDPB@AEC?GOR`@WoABEJCBD~@pATTD?LRv@`@n@x@XL`@x@JLTPZ`@PLl@l@d@V^BRHVZ\\Z`@JH?LH\\?DBVZTNRXJJJBLNL\\PRXFl@A~@`@VPh@f@\\TTTFLXRT^JDV\\PBVPLBXADFv@LPFLXDDDRJLHTLp@HPTPNDl@ANEP?^XLZHHFJNHLZLDZVNPNDPVHXJL^~@f@b@r@Z^^RZn@\\Z`@d@\\z@t@`@T\\\\THXPVRBFRJF?PN\\RRZJBLPFBHPJJf@RC?@Dd@Tb@\\^FVG", "average_heartrate": null, "average_speed": 2.479, "streak": 1}, {"run_id": 8086045948, "name": "\u508d\u665a\u8dd1\u6b65", "distance": 4650.7, "moving_time": "0:33:41", "type": "Run", "start_date": "2022-11-08 09:36:03+00:00", "start_date_local": "2022-11-08 17:36:03", "location_country": "\u671b\u6c5f\u897f\u8def, \u957f\u5b81\u793e\u533a\u670d\u52a1\u4e2d\u5fc3, \u5408\u80a5\u56fd\u5bb6\u9ad8\u65b0\u6280\u672f\u4ea7\u4e1a\u5f00\u53d1\u533a, \u8700\u5c71\u533a, \u5408\u80a5\u5e02, \u5b89\u5fbd\u7701, \u4e2d\u56fd", "summary_polyline": "}lhaEsnyiUJJHPFBFRD\\?j@Dd@EzAAt@Bt@?~AG^@JA|@@TCT@REJCx@D|@E\\?^@RCRA\\Bn@AzDEN?d@Ed@Ct@MZ_@`@aAb@_@BOCCFSLg@DcAVg@@KBc@@{@Es@OSK{@o@S[WUk@w@O_@Mu@Ak@BME_@Mg@OYEAKOWQ]OYQSQKQWk@I[GgAQwAWk@U]a@_@_AQ[Ac@Bi@PyARs@AgA@k@G_@?i@Dy@Rc@Tm@h@GNOJOREHo@t@k@Pu@Ca@KiAm@QYUk@GYOc@Q}@OQO[SQIO_A}@g@WgAQGEQSWeACk@B_@Ae@I_@?UI}@@SAW@IAKDMJO`@[l@S\\Q`@]RId@[V]P_AAO@MAG?kALq@?SHg@Zy@BQ?KEEe@G_@?YGu@Ci@ICMJMDSPW@Ml@kAb@o@^o@XUT[NIJYDEFBFAJOdAw@LYHGRKJBXSFKNGZUPAPDRM`A]tA]j@CTKL@h@GD@HCT?bAGL@HAR?TBJ?JBd@?ZHp@Dl@LNANHv@PLHpA`@JFNB`@RHH@BEJCBe@?OFKLCNN@HHh@VZLBFPL|C~A`@\\Rb@Nh@BpCDd@CVBBB|@Nr@NL\\Nv@DVDHCVHlAdA^^\\VNTb@d@FLD@Vh@JJT`@HD?D@FJKRI", "average_heartrate": null, "average_speed": 2.301, "streak": 1}, {"run_id": 8129782904, "name": "\u5348\u540e\u8dd1\u6b65", "distance": 4575.2, "moving_time": "0:31:09", "type": "Run", "start_date": "2022-11-17 09:18:46+00:00", "start_date_local": "2022-11-17 17:18:46", "location_country": "\u77f3\u83b2\u5357\u8def, \u957f\u5b81\u793e\u533a\u670d\u52a1\u4e2d\u5fc3, \u5408\u80a5\u56fd\u5bb6\u9ad8\u65b0\u6280\u672f\u4ea7\u4e1a\u5f00\u53d1\u533a, \u8700\u5c71\u533a, \u5408\u80a5\u5e02, \u5b89\u5fbd\u7701, \u4e2d\u56fd", "summary_polyline": "ogiaEioziUWUJRVLDCl@^VP@FdCvANN`@TNNT`@H^`@hHJd@JNVLl@D^CTBTLb@`@\\TJNVN`@b@FBb@f@f@z@`@f@HRJL`@t@BFn@hAFTBrAAlAE\\AvAF~@GlA@r@Cd@BbAGvB?z@GjA@~BM`FETQb@MHCFOF_AVI?MFU@OFq@HQFa@Fk@BWFS?cAIcAWm@a@YWi@q@USSYQc@Ii@C{AIi@O[WYk@[GAOGg@e@EOKKMo@Ci@Gc@?UQgA]m@[Ye@Ue@Mi@CQ@a@Ja@N{@Hk@@WAICs@B]EO@k@Ec@?]J_@Ri@\\[Vg@l@OXOTOLy@Z_@?a@Ek@Qg@YKOYc@GQOq@M[AKYy@u@cA_@[CGc@]o@Ys@MOQ[w@OkA?WIkAAs@Ec@@k@HS^e@\\MPMh@Q\\ULEXS`@m@FMLq@@_ABi@DW@]He@\\aAHa@EGOGc@CKCa@EaAGIEYCACPWf@wAd@u@X_@Xc@BIZYl@s@HE@EZ_@`@UXU@EAGh@e@h@UTQRGLKRIb@If@Sb@Iv@WTEFCP@^IVDr@Ib@Cv@BTAPBRET?|@HJ?d@LJ?RHJAl@NLFh@Lb@NBBL?VFFAFG", "average_heartrate": null, "average_speed": 2.448, "streak": 1}, {"run_id": 8165689717, "name": "\u508d\u665a\u8dd1\u6b65", "distance": 6053.1, "moving_time": "0:44:07", "type": "Run", "start_date": "2022-11-25 09:36:25+00:00", "start_date_local": "2022-11-25 17:36:25", "location_country": "\u4e2d\u65b0\u8f6f\u4ef6, \u521b\u65b0\u5927\u9053, \u521b\u65b0\u4ea7\u4e1a\u56ed-\u4e00\u671f, \u5408\u80a5\u56fd\u5bb6\u9ad8\u65b0\u6280\u672f\u4ea7\u4e1a\u5f00\u53d1\u533a, \u8700\u5c71\u533a, \u5408\u80a5\u5e02, \u5b89\u5fbd\u7701, \u4e2d\u56fd", "summary_polyline": "}shaE}u{iULa@?ES?IGA?GL?HEHIAQ@MKEKF?GI@IMIgAB]FIEEGGCUCQ@ODECO?m@S]JML?HFZ?DGJ]DSHSDKEW@KADA@BCJ@NCb@Eh@Q`@IV@l@EL?^ERFx@ET?LHb@?^Ed@HvBK`@FH@^KV@JETFv@?lC@FDv@?`@E\\@JGNI\\@l@MTIDSEMBOFGFGLBJPJtB`ArAv@THTNNBLJFPJHR\\L^NbCDbBPvAHVNRNFRBz@?d@Ll@f@RTv@l@RVNJ^d@j@~@`@j@DLhAhBPf@D`ACj@@d@ClA?dCGnB@t@Gd@Dp@EH@lAAb@C`GEzA?lBSx@WZIDc@Jq@FwBj@s@HaAHkAIq@OG?m@_@u@y@a@g@a@s@Mi@EsBG_@c@i@SSo@Y_@U_@g@Ke@GG?m@Im@Co@G_@Wo@Y]WQi@SYGOAg@BkAVw@H_BBeAAQ@YCYAY@QF{@b@{@j@y@lAAFSN_@NYD[@e@CQC[Mg@_@SSYo@]}AMc@OYm@w@[]q@e@[MMKo@KUKO]Mq@I}AUqCBw@HSNSnBaAVGLMVM\\i@To@Da@B{AHcA^oAJm@AIMIw@Iq@?m@OE?_@GAE@GZe@r@uAPWHSd@u@jAsAfAaAFOLOVM^WNEHIVIZWNBv@]v@URKF?f@MF@ZK|@In@I|AGXB~@A\\Dd@Bj@FR@XDr@PZBh@Rl@N`@PDCHi@TQTy@EaABSCM?_@AYEKFGBMAUBe@Gw@Fc@ES?UEO@EEg@@IAEDk@?i@Dm@CEE]Bc@EO?]@WDMCU?SEEAGDo@DCBM", "average_heartrate": null, "average_speed": 2.287, "streak": 1}, {"run_id": 8925110828, "name": "\u665a\u95f4\u8dd1\u6b65", "distance": 5201.2, "moving_time": "0:33:45", "type": "Run", "start_date": "2023-04-20 14:04:02+00:00", "start_date_local": "2023-04-20 22:04:02", "location_country": "\u54c8\u5c14\u6ee8\u5de5\u4e1a\u5927\u5b66\uff08\u6df1\u5733\uff09, 6, \u5e73\u5c71\u4e00\u8def, \u6843\u6e90\u8857\u9053, \u5357\u5c71\u533a, \u6df1\u5733\u5e02, \u5e7f\u4e1c\u7701, 518055, \u4e2d\u56fd", "summary_polyline": "kf{hCyiqvTk@DYCS@WLIHIVCVLd@DFJHZBVHJATBHDV?HBREj@AJCP@NGLQL]BWESU]YSi@Ic@FGAI@IE?HIBIIo@AUBWJWLKJAVJ`@FDDJPRb@JJHRAj@FZELBj@@HBBEZOFENe@?YYu@[UOAMEa@BOAKBIA]BMA_@DYJYRK^Dt@JTJHLFl@FdAGNEb@BXEDCN@POHSDU?[K]OSIGc@Ks@@KBk@Es@BOFSJMJGLGXDN?RPZPNTJP@FBXAXBp@ERBd@ERK@ETYHa@Em@OMCIYMWC{@BeACKB]AKHI?MHMPCHBn@BPDDBLDDv@TVCPDVEhADRMXIJKBMFGGs@IWOQi@KOFECG?[@OEk@@GA_@DUHSJKRCJATJ\\DBJTt@TN?H@P@FE`@@LC`@@d@E`@[BO@YFQM_@QOq@Mk@BeACQDW@]JG?INGDELCd@Jj@v@VVD`@@TEFEHBd@GL@t@KHGN[Bc@CUIKGO_@QYGOBUAYFOEi@F_@CG@e@VITAb@?PJj@FD\\Jt@DP?HEn@GHCd@?f@OV_@B_@Oi@GMUOE@MEeAJGDm@BGAk@AQFm@n@Tr@HPLLNHL@VETBb@Il@AV@RCVKFIHO@SFOCYIU[SUIG@KAi@DSCSDSAeA@MFWb@IFCLRv@n@JPHVBBCD?HEDA\\DXENDZ?LG^EHMBAFO?GBC@MKm@CGUMYK_A?GBUCeAFGCWHe@d@Fr@Xx@LFh@BZGT?HED@NCf@BFANBJA\\SNc@CSFYEKOW_@Uw@?GBc@@UAMDm@AKB?BGDM@GFIp@?f@FPCHZL`@DNEL?r@KR@h@Aj@KNIHO?KDMAe@OYSS_@Iu@JYAQD_@?", "average_heartrate": null, "average_speed": 2.568, "streak": 1}, {"run_id": 8935913949, "name": "\u508d\u665a\u8dd1\u6b65", "distance": 5201.9, "moving_time": "0:34:04", "type": "Run", "start_date": "2023-04-22 11:39:16+00:00", "start_date_local": "2023-04-22 19:39:16", "location_country": "\u54c8\u5c14\u6ee8\u5de5\u4e1a\u5927\u5b66\uff08\u6df1\u5733\uff09, 6, \u5e73\u5c71\u4e00\u8def, \u6843\u6e90\u8857\u9053, \u5357\u5c71\u533a, \u6df1\u5733\u5e02, \u5e7f\u4e1c\u7701, 518055, \u4e2d\u56fd", "summary_polyline": "{e{hCgjqvTMAQBS@_@Ck@j@K\\ATHb@LR\\PV?PEJ@DDF@^KR@`@GH@HADGVCRUFKCg@EOEGGUQMSGIBYCaBDMGOAa@NKJKRBREZBNTb@F@DFh@LN?XIL@FBVG`@AFDLDHCl@g@BYCQCc@ECOYOG?CQIGAE@KAUFYEGDK@WEc@DEAYDABMHKJKV@VF^J^LBHFZJf@EB@V?ZDz@E\\KX]@g@K_@Q_@OKk@Ea@@ECSBQAcA?OLODQ`@CP?VFZV`@VJP@FBBCL@h@EH?BBNCl@@RA\\QPONY@OG_@Ua@SSUOsAAKBMAED]Ag@B_@TMVAz@BXLXRDHD`@DxAOhA@BEFED?LIP_@@QO]AQGIYGCGECY?IFEAE@CEK?UBOEcAGSDQJSb@Ar@FNLHTZZBn@C^FFEXAF@HFNBd@WFIRm@Ea@IMCOYWQKKAM@{@CSB]Ae@FIA[VGJETAj@F^LN\\PB?NDh@AVEL@f@ELE`@DRGJKL_@BQ@[AEGK?OWYGEa@EK@ULEEOE_@DQCUBSEQ@]NILCNCh@@\\JRRNLDJ?RFRENDLCNBb@@LCf@CFGFCZYH[Ku@YWc@SICOBQ?IBi@CGBIAKBa@GMBKFU\\IV?XBRHPHJTPRBHFH@|ASF@PA^FLAJGVYBQ@QGc@CIUYWOSCw@BUAOBGCSBg@AYNKLCTGLA^@RNZTNHBRLN?F@n@GHEL?REH?FDp@QRSHU@Q?KUs@OMSK[AMBOEW?IDc@BE@_@ASJCHUTMn@DTR^TRLBl@EF@NGHBj@CZHN?RIb@SDKBWIk@O[QUg@Q]BSCEBO?_ACYB]NKLQ^?ZHh@HLNNVHXBJEf@E^BfA@HCZQFMHGHUAYKe@W[OGUGg@BSCGDW?", "average_heartrate": null, "average_speed": 2.545, "streak": 1}]